kcleaner/__init__.py
kcleaner/cli.py
kcleaner/core/__init__.py
kcleaner/core/config.py
kcleaner/core/exceptions.py
kcleaner/core/styles.py
kcleaner/core/types.py
kcleaner/utils/__init__.py
kcleaner/utils/file_utils.py
kcleaner/utils/logging_utils.py
kcleaner/utils/simple.py
kcleaner/utils/validator.py
kcleaner_py-0.2.1.dist-info/licenses/LICENSE
kcleaner_py-0.2.1.dist-info/METADATA
kcleaner_py-0.2.1.dist-info/WHEEL
kcleaner_py-0.2.1.dist-info/entry_points.txt
kcleaner_py-0.2.1.dist-info/top_level.txt
kcleaner_py-0.2.1.dist-info/RECORD
