Metadata-Version: 2.4
Name: kcleaner-py
Version: 0.2.1
Summary: Secure CLI tool to identify and delete KATE backup files (*.~ and .*~) with user confirmation.
Home-page: https://github.com/skye-cyber/kcleaner
Author: Skye
Author-email: swskye17@gmail.com
License: GNU v3
Keywords: dir_clean,tmp_clean,scanner,cleaner
Classifier: Environment :: Console
Classifier: Natural Language :: English
Classifier: Operating System :: OS Independent
Classifier: Programming Language :: Python
Classifier: Programming Language :: Python :: 3 :: Only
Classifier: Programming Language :: Python :: 3.12
Classifier: Programming Language :: Python :: 3.13
Requires-Python: >=3.8
License-File: LICENSE
Dynamic: author
Dynamic: author-email
Dynamic: classifier
Dynamic: description
Dynamic: description-content-type
Dynamic: home-page
Dynamic: keywords
Dynamic: license
Dynamic: license-file
Dynamic: requires-python
Dynamic: summary
